lotad/__init__.py
lotad/cli.py
lotad/config.py
lotad/config_wizard.py
lotad/connection.py
lotad/data_analysis.py
lotad/db_compare.py
lotad/logger.py
lotad/utils.py
lotad/data/README.md
lotad/data/duckdb_to_postgres_data_types.json
lotad/data/duckdb_to_sqlite_data_types.json
lotad/data/postgres_to_duckdb_data_types.json
lotad/data/postgres_to_sqlite_data_types.json
lotad/queries/duckdb/config_builder_ignore_columns_create_table.sql
lotad/queries/duckdb/config_builder_ignore_columns_get_column_val_intersect.sql
lotad/queries/duckdb/data_analysis_set_data_drift_for_table.sql
lotad/queries/duckdb/db_compare_create_tmp_table_merge.sql
lotad/queries/duckdb/default_select_from_table.sql
lotad/queries/duckdb/drift_analysis_extend_data_drift_summary.sql
lotad/queries/duckdb/get_schema.sql
lotad/queries/duckdb/list_tables.sql
lotad/queries/postgres/default_select_from_table.sql
lotad/queries/postgres/get_schema.sql
lotad/queries/postgres/list_tables.sql
lotad/queries/sqlite/default_select_from_table.sql
lotad/queries/sqlite/get_schema.sql
lotad/queries/sqlite/list_tables.sql
lotad/reports/db_comparison_report.j2
lotad-0.2.1.dist-info/METADATA
lotad-0.2.1.dist-info/WHEEL
lotad-0.2.1.dist-info/entry_points.txt
lotad-0.2.1.dist-info/licenses/LICENSE
lotad-0.2.1.dist-info/RECORD
