Metadata-Version: 2.4
Name: lotad
Version: 0.2.1
Summary: Lotad helps you identify schema changes, data differences, and structural modifications between database versions.
License: MIT
License-File: LICENSE
Requires-Python: >=3.12
Requires-Dist: click>=8.1.8
Requires-Dist: duckdb>=1.1.3
Requires-Dist: faker>=34.0.0
Requires-Dist: inquirer>=3.4.0
Requires-Dist: jinja2>=3.1.5
Requires-Dist: orjson>=3.10.13
Requires-Dist: pandas>=2.2.3
Requires-Dist: pytest>=8.3.4
Requires-Dist: python-dotenv>=1.0.1
Requires-Dist: pyyaml>=6.0.2
Requires-Dist: questionary>=2.1.0
Requires-Dist: sql-metadata>=2.15.0
Requires-Dist: sqlparse>=0.5.3
Requires-Dist: structlog>=24.4.0
Requires-Dist: xxhash>=3.5.0
